{"coordinates": {"latitude": 42.32938, "longitude": -83.1621}, "is_closed": false, "image_url": "https://s3-media4.fl.yelpcdn.com/bphoto/qK69boDj-NRwk8kbPJx_Eg/o.jpg", "price": "$", "hours": [{"hours_type": "REGULAR", "is_open_now": false, "open": [{"end": "0000", "is_overnight": false, "day": 0, "start": "1100"}, {"end": "0000", "is_overnight": false, "day": 1, "start": "1100"}, {"end": "0000", "is_overnight": false, "day": 2, "start": "1100"}, {"end": "0000", "is_overnight": false, "day": 3, "start": "1100"}, {"end": "0100", "is_overnight": true, "day": 4, "start": "1100"}, {"end": "0100", "is_overnight": true, "day": 5, "start": "1100"}, {"end": "0000", "is_overnight": false, "day": 6, "start": "1200"}]}], "phone": "+13137246535", "location": {"address2": null, "city": "Dearborn", "address1": "10419 Ford Rd", "address3": "", "zip_code": "48126", "country": "US", "state": "MI"}, "term": "restaurants", "is_claimed": true, "url": "https://www.yelp.com/biz/taystees-burgers-dearborn?adjust_creative=92p07_JjKyriZTQxAXRiKQ&utm_campaign=yelp_api_v3&utm_medium=api_v3_business_lookup&utm_source=92p07_JjKyriZTQxAXRiKQ", "id": "taystees-burgers-dearborn", "name": "Taystee's Burgers", "review_count": 47, "categories": [{"title": "Burgers", "alias": "burgers"}, {"title": "Fast Food", "alias": "hotdogs"}], "photos": ["https://s3-media2.fl.yelpcdn.com/bphoto/qK69boDj-NRwk8kbPJx_Eg/o.jpg", "https://s3-media3.fl.yelpcdn.com/bphoto/fQdn7pgDK5h5N_kZcCST1Q/o.jpg", "https://s3-media2.fl.yelpcdn.com/bphoto/3TDI-lydBg-wq6bX535lBw/o.jpg"], "rating": 4.5}