{"coordinates": {"latitude": 42.375996659073, "longitude": -71.115127405266}, "is_closed": false, "image_url": "https://s3-media3.fl.yelpcdn.com/bphoto/TmbUxoctfMve68Be1P9pxg/o.jpg", "phone": "+16174964595", "location": {"address2": "", "city": "Cambridge", "address1": "45 Quincy St", "address3": "", "zip_code": "02138", "country": "US", "state": "MA"}, "term": "attractions", "is_claimed": false, "url": "https://www.yelp.com/biz/memorial-hall-cambridge?adjust_creative=92p07_JjKyriZTQxAXRiKQ&utm_campaign=yelp_api_v3&utm_medium=api_v3_business_lookup&utm_source=92p07_JjKyriZTQxAXRiKQ", "id": "memorial-hall-cambridge", "name": "Memorial Hall", "review_count": 13, "categories": [{"title": "Landmarks & Historical Buildings", "alias": "landmarks"}], "photos": ["https://s3-media3.fl.yelpcdn.com/bphoto/TmbUxoctfMve68Be1P9pxg/o.jpg", "https://s3-media2.fl.yelpcdn.com/bphoto/4eTbu7buliVwXKT_EYjyFQ/o.jpg", "https://s3-media2.fl.yelpcdn.com/bphoto/eNP0vATHaZq2O9hKIwVNzw/o.jpg"], "rating": 4.5}