{"coordinates": {"latitude": -35.239399, "longitude": 149.0937042}, "is_closed": false, "image_url": "", "phone": "+61262534964", "location": {"address2": null, "city": "Bruce", "address1": "Thynne St", "address3": null, "zip_code": "2617", "country": "AU", "state": "ACT"}, "term": "restaurants", "is_claimed": false, "url": "https://www.yelp.com/biz/cafe-momo-bruce-2?adjust_creative=92p07_JjKyriZTQxAXRiKQ&utm_campaign=yelp_api_v3&utm_medium=api_v3_business_lookup&utm_source=92p07_JjKyriZTQxAXRiKQ", "id": "cafe-momo-bruce-2", "name": "Cafe Momo", "review_count": 3, "categories": [{"alias": "cafes", "title": "Cafes"}, {"alias": "catering", "title": "Caterers"}], "photos": [], "rating": 4.0}