{"coordinates": {"latitude": -37.8177872, "longitude": 144.9580536}, "is_closed": false, "image_url": "https://s3-media3.fl.yelpcdn.com/bphoto/8PzMf-dTaP0r5seV65fvTg/o.jpg", "price": "$", "hours": [{"hours_type": "REGULAR", "is_open_now": false, "open": [{"end": "1500", "is_overnight": false, "start": "1030", "day": 0}, {"end": "1500", "is_overnight": false, "start": "1030", "day": 1}, {"end": "1500", "is_overnight": false, "start": "1030", "day": 2}, {"end": "1500", "is_overnight": false, "start": "1030", "day": 3}, {"end": "1500", "is_overnight": false, "start": "1030", "day": 4}]}], "phone": "+6186106316", "location": {"address2": "", "city": "Melbourne", "address1": "7/480 Collins St", "address3": "", "zip_code": "3000", "country": "AU", "state": "VIC"}, "term": "restaurants", "is_claimed": false, "url": "https://www.yelp.com/biz/mason-dixon-melbourne?adjust_creative=92p07_JjKyriZTQxAXRiKQ&utm_campaign=yelp_api_v3&utm_medium=api_v3_business_lookup&utm_source=92p07_JjKyriZTQxAXRiKQ", "id": "mason-dixon-melbourne", "name": "Mason Dixon", "review_count": 6, "categories": [{"alias": "tradamerican", "title": "American (Traditional)"}, {"alias": "sandwiches", "title": "Sandwiches"}], "photos": ["https://s3-media3.fl.yelpcdn.com/bphoto/8PzMf-dTaP0r5seV65fvTg/o.jpg", "https://s3-media1.fl.yelpcdn.com/bphoto/yGZ9y8UnIqwR6D8yf6O4tA/o.jpg", "https://s3-media1.fl.yelpcdn.com/bphoto/V_lZsNTfTB-FKMEo42xLOg/o.jpg"], "rating": 4.5}