{"coordinates": {"latitude": -33.8643112, "longitude": 151.2113495}, "is_closed": false, "image_url": "https://s3-media4.fl.yelpcdn.com/bphoto/z0HmXOSmm5ucXAVY5V-68A/o.jpg", "hours": [{"hours_type": "REGULAR", "is_open_now": false, "open": [{"end": "1700", "is_overnight": false, "day": 0, "start": "0700"}, {"end": "1700", "is_overnight": false, "day": 1, "start": "0700"}, {"end": "1700", "is_overnight": false, "day": 2, "start": "0700"}, {"end": "1700", "is_overnight": false, "day": 3, "start": "0700"}, {"end": "1700", "is_overnight": false, "day": 4, "start": "0700"}]}], "phone": "", "term": "restaurants", "location": {"address2": "", "city": "Sydney", "address1": "45 Phillip St", "address3": "", "zip_code": "2000", "country": "AU", "state": "NSW"}, "is_claimed": false, "url": "https://www.yelp.com/biz/phillips-heritage-cafe-and-gourmet-eatery-sydney?adjust_creative=92p07_JjKyriZTQxAXRiKQ&utm_campaign=yelp_api_v3&utm_medium=api_v3_business_lookup&utm_source=92p07_JjKyriZTQxAXRiKQ", "id": "phillips-heritage-cafe-and-gourmet-eatery-sydney", "name": "Phillips Heritage Cafe & Gourmet Eatery", "review_count": 2, "categories": [{"title": "Cafes", "alias": "cafes"}], "photos": ["https://s3-media3.fl.yelpcdn.com/bphoto/z0HmXOSmm5ucXAVY5V-68A/o.jpg", "https://s3-media3.fl.yelpcdn.com/bphoto/7nILq4wA9h_zaKdajo7w4A/o.jpg"], "rating": 4.0}