{"coordinates": {"latitude": 48.860385, "longitude": 2.293561}, "is_closed": false, "hours": [{"hours_type": "REGULAR", "is_open_now": false, "open": [{"is_overnight": false, "end": "2200", "start": "1000", "day": 0}, {"is_overnight": false, "end": "2200", "start": "1000", "day": 1}, {"is_overnight": false, "end": "2200", "start": "1000", "day": 2}, {"is_overnight": false, "end": "2200", "start": "1000", "day": 3}, {"is_overnight": false, "end": "2200", "start": "1000", "day": 4}, {"is_overnight": false, "end": "2200", "start": "1000", "day": 5}, {"is_overnight": false, "end": "2200", "start": "1000", "day": 6}]}], "image_url": "https://s3-media2.fl.yelpcdn.com/bphoto/auwh963JHNTe26sANASE9Q/o.jpg", "price": "\u20ac\u20ac\u20ac\u20ac", "phone": "+33825010101", "location": {"address2": "", "city": "Paris", "address1": "Port de la Bourdonnais", "address3": "", "zip_code": "75007", "country": "FR", "state": "75"}, "term": "attractions", "is_claimed": true, "url": "https://www.yelp.com/biz/bateaux-parisiens-paris?adjust_creative=92p07_JjKyriZTQxAXRiKQ&utm_campaign=yelp_api_v3&utm_medium=api_v3_business_lookup&utm_source=92p07_JjKyriZTQxAXRiKQ", "id": "bateaux-parisiens-paris", "name": "Bateaux Parisiens", "review_count": 118, "categories": [{"title": "Boat Charters", "alias": "boatcharters"}, {"title": "French", "alias": "french"}], "photos": ["https://s3-media3.fl.yelpcdn.com/bphoto/auwh963JHNTe26sANASE9Q/o.jpg", "https://s3-media4.fl.yelpcdn.com/bphoto/pHJvGTatXGgBSg5Aljg_hA/o.jpg", "https://s3-media3.fl.yelpcdn.com/bphoto/6PDpVwzrmwkCpwpkBwlm-g/o.jpg"], "rating": 3.5}