{"coordinates": {"latitude": -42.8814888, "longitude": 147.3360748}, "is_closed": false, "image_url": "", "phone": "+61499506700", "location": {"address2": "Hobart Waterfront", "city": "Hobart", "address1": "35 Hunter St", "address3": "", "zip_code": "7000", "country": "AU", "state": "TAS"}, "term": "hotels", "is_claimed": false, "url": "https://www.yelp.com/biz/moto-adventure-hobart?adjust_creative=92p07_JjKyriZTQxAXRiKQ&utm_campaign=yelp_api_v3&utm_medium=api_v3_business_lookup&utm_source=92p07_JjKyriZTQxAXRiKQ", "id": "moto-adventure-hobart", "name": "Moto Adventure", "review_count": 0, "categories": [{"title": "Motorcycle Rental", "alias": "motorcycle_rental"}], "photos": [], "rating": 0.0}