{"coordinates": {"latitude": 53.5662499, "longitude": -1.58836}, "is_closed": false, "image_url": "https://s3-media2.fl.yelpcdn.com/bphoto/sLQNokJYh5mhVdH-qEu3tg/o.jpg", "price": "\u00a3\u00a3", "phone": "+441226790427", "location": {"address2": "", "city": "Barnsley", "address1": "Bark House Lane", "address3": "Cawthorne", "zip_code": "S75 4AT", "country": "GB", "state": "XSY"}, "term": "attractions", "is_claimed": false, "url": "https://www.yelp.com/biz/cannon-hall-farm-barnsley?adjust_creative=92p07_JjKyriZTQxAXRiKQ&utm_campaign=yelp_api_v3&utm_medium=api_v3_business_lookup&utm_source=92p07_JjKyriZTQxAXRiKQ", "id": "cannon-hall-farm-barnsley", "name": "Cannon Hall Farm", "review_count": 11, "categories": [{"alias": "zoos", "title": "Zoos"}, {"alias": "farmersmarket", "title": "Farmers Market"}], "photos": ["https://s3-media2.fl.yelpcdn.com/bphoto/sLQNokJYh5mhVdH-qEu3tg/o.jpg", "https://s3-media4.fl.yelpcdn.com/bphoto/Bz7chZIQoRTpYSl3_kCz0Q/o.jpg", "https://s3-media3.fl.yelpcdn.com/bphoto/Vh5px0YTjY_YruNv2zCjqg/o.jpg"], "rating": 4.5}